README.md
setup.py
PyBean/__init__.py
PyBean/banner.py
PyBean/bean.py
PyBean/by.py
PyBean/instance.py
PyBean/ioc.py
pyBean.egg-info/PKG-INFO
pyBean.egg-info/SOURCES.txt
pyBean.egg-info/dependency_links.txt
pyBean.egg-info/top_level.txt
test/__init__.py
test/testIoc.py
test/testxml.py
test/dao/__init__.py
test/dao/bookdao.py
test/dao/paydao.py
test/imp/__init__.py
test/imp/bookImp.py
test/imp/payImp.py