Metadata-Version: 2.1
Name: pyBean
Version: 0.0.26
Summary: An example Python IOC looks like Spring
Home-page: https://pypi.org/project/pyBean/
Author: Archer_Lee.chen
Author-email: liruochen01@outlook.com
License: LICENSE.txt
Platform: UNKNOWN
Classifier: Programming Language :: Python :: 3
Classifier: License :: OSI Approved :: MIT License
Classifier: Operating System :: OS Independent
